README.md
poetics.py
setup.cfg
setup.py
poetics.egg-info/PKG-INFO
poetics.egg-info/SOURCES.txt
poetics.egg-info/dependency_links.txt
poetics.egg-info/requires.txt
poetics.egg-info/top_level.txt