Metadata-Version: 1.0
Name: poetics
Version: 0.0.1
Summary: computational poetry
Home-page: https://github.com/machow/poetics
Author: Michael Chow
Author-email: mc_al_github@fastmail.com
License: UNKNOWN
Platform: UNKNOWN
